setup.cfg
setup.py
dynamo_lock/__init__.py
dynamo_lock/config.py
dynamo_lock/dynalock.py
dynamo_lock.egg-info/PKG-INFO
dynamo_lock.egg-info/SOURCES.txt
dynamo_lock.egg-info/dependency_links.txt
dynamo_lock.egg-info/requires.txt
dynamo_lock.egg-info/top_level.txt