Metadata-Version: 1.1
Name: dynamo-lock
Version: 0.1.1
Summary: A lock implementation with AWS dynamo db
Home-page: https://github.com/MarechJ/dynamodb-lock
Author: Julien Marechal
Author-email: julien.marechal35@gmail.com
License: MIT
Download-URL: https://github.com/MarechJ/dynamodb-lock/archive/0.1.1.tar.gz
Keywords: dynamo,dynamodb,aws,lock,distributed,locking
Platform: UNKNOWN
